{
  "slug": "devichan-247",
  "chinese": "視訊會議",
  "pinyin": "shìxùn huìyì",
  "meaning": "video conference, video meeting",
  "description": "",
  "examples": [
    {
      "chinese": "視訊會議怎麼使用？",
      "translation": "How do you use video conferencing?"
    },
    {
      "chinese": "我們十點有視訊會議。",
      "translation": "We have a video conference at 10 o'clock."
    },
    {
      "chinese": "視訊會議已經成為日常。",
      "translation": "Video meetings have become routine."
    }
  ],
  "category": "chengyu",
  "categoryName": "Chinese Idioms",
  "relatedWords": [],
  "sourceUrl": "https://www.devichan-chigoworld.com/use-china/%e3%80%8c%e5%b7%a3%e3%81%94%e3%82%82%e3%82%8a%e6%b6%88%e8%b2%bb%e3%80%8d%e3%80%81%e3%80%8c%e3%83%93%e3%83%87%e3%82%aa%e4%bc%9a%e8%ad%b0%e3%80%8d%e3%81%af%e4%b8%ad%e5%9b%bd%e8%aa%9e%e3%81%a7%e4%bd%95",
  "sourceEnglish": "video conference"
}
