{
  "slug": "devichan-207",
  "chinese": "口碑",
  "pinyin": "kǒubēi",
  "meaning": "word of mouth, reputation",
  "description": "",
  "examples": [
    {
      "chinese": "口碑行銷",
      "translation": "word-of-mouth marketing"
    },
    {
      "chinese": "這家餐廳口碑很好。",
      "translation": "This restaurant has a great reputation."
    },
    {
      "chinese": "好的口碑很重要。",
      "translation": "Good word of mouth is important."
    }
  ],
  "category": "net",
  "categoryName": "Internet Slang",
  "relatedWords": [],
  "sourceUrl": "https://www.devichan-chigoworld.com/use-china/733",
  "sourceEnglish": "word of mouth"
}
