{
  "slug": "devichan-293",
  "chinese": "離題",
  "pinyin": "lítí",
  "meaning": "to digress, to stray from the topic",
  "description": "",
  "examples": [
    {
      "chinese": "我們離題了，回到正題吧。",
      "translation": "We've gone off-topic, let's get back to the point."
    },
    {
      "chinese": "他講話常常離題。",
      "translation": "He often goes off-topic when speaking."
    },
    {
      "chinese": "不好意思，我離題了。",
      "translation": "Sorry, I digressed."
    }
  ],
  "category": "net",
  "categoryName": "Internet Slang",
  "relatedWords": [],
  "sourceUrl": "https://www.devichan-chigoworld.com/use-china/%e4%b8%ad%e5%9b%bd%e8%aa%9e%e3%81%a7%e3%80%8c%e8%a9%b1%e3%81%8c%e3%81%9d%e3%82%8c%e3%82%8b%e3%80%8d%e3%81%af%e4%bd%95%e3%81%a8%e3%81%84%e3%81%86%ef%bc%9f",
  "sourceEnglish": "get off topic, digress,"
}
