{
  "slug": "bao",
  "chinese": "包办婚姻",
  "pinyin": "bāo bàn hūn yīn",
  "meaning": "คลุมถุงชน",
  "description": "การแต่งงานที่พ่อแม่หรือผู้ใหญ่เป็นคนจัดการหาคู่ให้ โดยที่เจ้าตัวอาจจะไม่ได้เต็มใจ",
  "examples": [
    {
      "chinese": "下周估计能到家,希望我的包办婚姻能成功",
      "translation": "น่าจะถึงบ้านอาทิตย์หน้า หวังว่าการคลุมถุงชนของฉันจะไปได้สวยนะ"
    },
    {
      "chinese": "和包办婚姻的老婆在一起一年了",
      "translation": "อยู่กับภรรยาที่ผู้ใหญ่หาให้มาปีนึงแล้ว"
    },
    {
      "chinese": "我现在需要一场包办婚姻,自由恋爱已经谈够了",
      "translation": "ตอนนี้ฉันต้องการการคลุมถุงชนแล้วล่ะ เบื่อจะหาแฟนเองแล้ว"
    }
  ],
  "category": "nannv",
  "categoryName": "ความรัก/การแต่งงาน",
  "relatedWords": [],
  "sourceUrl": "https://chineself.com/bao/"
}