{
  "slug": "devichan-256",
  "chinese": "當真",
  "pinyin": "dàngzhēn",
  "meaning": "เชื่อจริง, เอาจริงเอาจัง",
  "description": "",
  "examples": [
    {
      "chinese": "萬一哪一天我把你這些話當真怎麼辦？",
      "translation": "ถ้าวันหนึ่งฉันเชื่อคำพูดพวกนี้ของเธอจริงๆ จะทำยังไง?"
    },
    {
      "chinese": "他開玩笑的，不要當真。",
      "translation": "เขาพูดเล่นเฉยๆ อย่าเอาจริงเอาจัง"
    },
    {
      "chinese": "你不會把這當真吧？",
      "translation": "เธอไม่ได้เชื่อจริงหรอกใช่ไหม?"
    }
  ],
  "category": "net",
  "categoryName": "ศัพท์อินเทอร์เน็ต",
  "relatedWords": [],
  "sourceUrl": "https://www.devichan-chigoworld.com/use-china/%e4%b8%ad%e5%9b%bd%e8%aa%9e%e3%81%a7%e3%80%8c%e7%9c%9f%e3%81%ab%e5%8f%97%e3%81%91%e3%82%8b%e3%80%81%e6%9c%ac%e6%b0%97%e3%81%ab%e3%81%99%e3%82%8b%e3%80%8d%e3%80%81%e3%80%8c%e8%88%88%e3%81%96%e3%82%81",
  "sourceEnglish": "take seriously"
}
