{
  "slug": "devichan-121",
  "chinese": "啃老族",
  "pinyin": "kĕnlǎozú",
  "meaning": "คนกินบุญพ่อแม่, คนอาศัยพ่อแม่",
  "description": "",
  "examples": [
    {
      "chinese": "畢業即失業只能回家當啃老族？",
      "translation": "เรียนจบแล้วตกงานก็ต้องกลับบ้านกินบุญพ่อแม่?"
    },
    {
      "chinese": "他30歲了還是啃老族。",
      "translation": "เขาอายุ 30 แล้วยังกินบุญพ่อแม่อยู่"
    },
    {
      "chinese": "很多年輕人被迫成為啃老族。",
      "translation": "วัยรุ่นหลายคนถูกบังคับให้ต้องพึ่งพ่อแม่"
    }
  ],
  "category": "net",
  "categoryName": "ศัพท์อินเทอร์เน็ต",
  "relatedWords": [],
  "sourceUrl": "https://www.devichan-chigoworld.com/use-china/%e4%b8%ad%e5%9b%bd%e8%aa%9e%e3%81%a7%e3%80%8c%e6%9c%88%e5%85%89%e6%97%8f%e3%80%8d%e3%80%81%e3%80%8c%e5%95%83%e8%80%81%e6%97%8f%e3%80%8d%e3%81%a8%e3%81%af%ef%bc%9f",
  "sourceEnglish": "NEET (Not in Education, Employment or Training)"
}
