{
  "slug": "ao",
  "chinese": "熬穿了",
  "pinyin": "áo chuān le",
  "meaning": "夜通し、徹夜",
  "description": "",
  "examples": [
    {
      "chinese": "一个星期熬穿了两次",
      "japanese": "一週間に徹夜を2回した"
    },
    {
      "chinese": "年轻人在周末吃早餐,不是因为起得早,是熬穿了",
      "japanese": "若い人が週末に朝外で食事していたら、早起きしたのではなく朝帰りだ"
    },
    {
      "chinese": "明知今天要上一天班还熬夜熬穿了,现在生不如死",
      "japanese": "明らかに今日は出勤後に夜通し徹夜だ、もう死んでしまいたい"
    }
  ],
  "category": "uncategorized",
  "categoryName": "未分類",
  "relatedWords": [],
  "sourceUrl": "https://chineself.com/ao/"
}