{
  "slug": "san",
  "chinese": "三八",
  "pinyin": "sān bā",
  "meaning": "①バカもの、アホ ②ケチをつける、とやかく言う、おしゃべり",
  "description": "三八の一般的な意味は、3月8日の国際女性デー「三八妇女节」の略である。ただ、この「三八」は古くから閩南語で罵る言葉として用いられてきた。辞書には【新語】として「バカ、うすのろ、ひねくれもの」とある。死三八は「バカもの」などと訳す。",
  "examples": [
    {
      "chinese": "不能向死三八服软",
      "japanese": "馬鹿者に対しては引き下がることができない"
    },
    {
      "chinese": "你妈b,远离所有三八和二货",
      "japanese": "クソ野郎、すべてのバカとアホには近づくな"
    },
    {
      "chinese": "没忍住骂三八了",
      "japanese": "ケチをつけずにはいられなかった"
    }
  ],
  "category": "uncategorized",
  "categoryName": "未分類",
  "relatedWords": [],
  "sourceUrl": "https://chineself.com/san/"
}