{
  "slug": "suo",
  "chinese": "所爱隔山海,山海皆可平",
  "pinyin": "suǒ ài gé shān hǎi, shān hǎi jiē kě píng",
  "meaning": "（男女の）愛の隔たりは克服できる",
  "description": "山と海の隔たりがあろうとも平らにできるということ。男女の愛を山と海に喩えたネット用語。所爱隔山海,山海亦可平も同じ。",
  "examples": [
    {
      "chinese": "所爱隔山海,山海皆可平,难平是人心",
      "japanese": "愛の隔たりは克服できる、克服できないのは人の心に原因がある"
    },
    {
      "chinese": "所爱隔山海,山海皆可平,海有舟可渡,山有路可行",
      "japanese": "愛の困難は克服できる、海には渡る舟があり、山には行く道がある"
    },
    {
      "chinese": "所爱隔山海,山海皆可平,生不遇你,世无如此欢喜",
      "japanese": "愛の隔たりは克服できる、あなたに会わなければこんなに幸せではなかったでしょう"
    }
  ],
  "category": "nannv",
  "categoryName": "恋愛・結婚",
  "relatedWords": [],
  "sourceUrl": "https://chineself.com/suo/"
}