{
  "slug": "devichan-107",
  "chinese": "抓猴",
  "pinyin": "zhuā hóu",
  "meaning": "바람피는 현장을 잡다, 불륜 현장을 잡다",
  "description": "",
  "examples": [
    {
      "chinese": "她請偵探去抓猴。",
      "translation": "그녀는 탐정을 고용해서 불륜 현장을 잡았다."
    },
    {
      "chinese": "被抓猴了，怎麼辦？",
      "translation": "현장에서 걸렸는데 어떡해?"
    },
    {
      "chinese": "抓猴抓到了，要離婚嗎？",
      "translation": "불륜 현장 잡았는데 이혼해야 해?"
    }
  ],
  "category": "net",
  "categoryName": "인터넷 용어",
  "relatedWords": [],
  "sourceUrl": "https://www.devichan-chigoworld.com/use-china/%e4%b8%ad%e5%9b%bd%e8%aa%9e%e3%81%ae%e3%80%8c%e5%85%88%e4%b8%8a%e8%bb%8a%e5%be%8c%e8%a3%9c%e7%a5%a8%e3%80%8d%e3%80%81%e3%80%8c%e6%8a%93%e7%8c%b4%e3%80%8d%e3%81%a8%e3%81%af%ef%bc%9f",
  "sourceEnglish": "catch the adultery on the spot"
}
