{
  "slug": "devichan-181",
  "chinese": "心結",
  "pinyin": "xīnjié",
  "meaning": "응어리, 마음의 짐",
  "description": "",
  "examples": [
    {
      "chinese": "兩人之間到底有沒有心結呢？",
      "translation": "두 사람 사이에 도대체 무슨 응어리가 있는 거야?"
    },
    {
      "chinese": "我想解開心結。",
      "translation": "나는 마음의 응어리를 풀고 싶어."
    },
    {
      "chinese": "他心裡有心結。",
      "translation": "그의 마음속에 응어리가 있어."
    }
  ],
  "category": "net",
  "categoryName": "인터넷 용어",
  "relatedWords": [],
  "sourceUrl": "https://www.devichan-chigoworld.com/use-china/%e4%b8%ad%e5%9b%bd%e8%aa%9e%e3%81%ae%e3%80%8c%e5%bf%83%e7%b5%90%e3%80%8d%e3%80%81%e3%80%8c%e5%92%8c%e5%a5%bd%e3%80%8d%e3%81%af%e3%81%a9%e3%82%93%e3%81%aa%e6%84%8f%e5%91%b3%ef%bc%9f",
  "sourceEnglish": "a feeling of discontentment, some ill feeling, something personal against"
}
