{
  "slug": "jiao",
  "chinese": "脚打后脑勺",
  "pinyin": "jiǎo dǎ hòu nǎo sháo",
  "meaning": "발이 뒤통수를 칠 정도로 바쁘다 / 눈코 뜰 새 없다",
  "description": "직역하면 「발로 뒤통수를 차다」가 되지만, 발을 빨리 놀려 매우 바쁘다는 것을 형용함.",
  "examples": [
    {
      "chinese": "节假后的周一又是脚打后脑勺 ​",
      "translation": "연휴 후 월요일은 또 미친 듯이 바쁘다"
    },
    {
      "chinese": "今天连跑四个地方,真是脚打后脑勺的一天呢",
      "translation": "오늘 네 군데나 돌았다, 정말 상상 초월로 바쁜 하루다"
    },
    {
      "chinese": "忙的脚打后脑勺的出差,忙里偷闲晚上泡个温泉",
      "translation": "눈코 뜰 새 없는 출장, 바쁜 와중에 짬을 내어 저녁에 온천을 했다"
    }
  ],
  "category": "uncategorized",
  "categoryName": "미분류",
  "relatedWords": [],
  "sourceUrl": "https://chineself.com/jiao/"
}
